mcp_server_office/__init__.py
mcp_server_office/__main__.py
mcp_server_office/office.py
mcp_server_office/tools.py
mcp_server_office-0.1.1.dist-info/METADATA
mcp_server_office-0.1.1.dist-info/WHEEL
mcp_server_office-0.1.1.dist-info/entry_points.txt
mcp_server_office-0.1.1.dist-info/RECORD
