Metadata-Version: 2.4
Name: mcp-server-office
Version: 0.1.1
Summary: A Model Context Protocol server providing tools to read/write docx files
Author: famano
Requires-Python: >=3.12
Requires-Dist: mcp[cli]>=1.2.0
Requires-Dist: python-docx>=1.1.2
Provides-Extra: dev
Requires-Dist: pytest-asyncio>=0.23.0; extra == 'dev'
Requires-Dist: pytest>=7.4.0; extra == 'dev'
